jeong_mul/__init__.py
jeong_mul/mul.py
jeong_mul-0.1.3.dist-info/METADATA
jeong_mul-0.1.3.dist-info/WHEEL
jeong_mul-0.1.3.dist-info/top_level.txt
jeong_mul-0.1.3.dist-info/RECORD
