Metadata-Version: 2.1
Name: jeong_mul
Version: 0.1.3
Summary: Default template for PDM package
Author-email: Jeonghoon2 <ukidd12@naver.com>
License: MIT
Requires-Python: >=3.9
